CODE_OF_CONDUCT.md
CONTRIBUTING.md
LICENSE.txt
MANIFEST.in
Makefile
README.md
requirements.txt
setup.cfg
setup.py
libioc/BridgeInterface.py
libioc/CommandQueue.py
libioc/Datasets.py
libioc/DevfsRules.py
libioc/Distribution.py
libioc/Filter.py
libioc/Firewall.py
libioc/Host.py
libioc/IPAddress.py
libioc/Jail.py
libioc/JailParams.py
libioc/Jails.py
libioc/LaunchableResource.py
libioc/ListableResource.py
libioc/Logger.py
libioc/MacAddress.py
libioc/Network.py
libioc/NetworkInterface.py
libioc/Pkg.py
libioc/Prompts.py
libioc/Release.py
libioc/Releases.py
libioc/Resource.py
libioc/ResourceBackup.py
libioc/ResourceSelector.py
libioc/ResourceUpdater.py
libioc/SecureTarfile.py
libioc/Types.py
libioc/VersionedResource.py
libioc/ZFS.py
libioc/ZFSShareStorage.py
libioc/__init__.py
libioc/decorators.py
libioc/errors.py
libioc/events.py
libioc/helpers.py
libioc/helpers_ioctl.py
libioc/helpers_object.py
libioc.egg-info/PKG-INFO
libioc.egg-info/SOURCES.txt
libioc.egg-info/dependency_links.txt
libioc.egg-info/requires.txt
libioc.egg-info/top_level.txt
libioc/Config/._Data.py
libioc/Config/Data.py
libioc/Config/Dataset.py
libioc/Config/Prototype.py
libioc/Config/__init__.py
libioc/Config/Host/__init__.py
libioc/Config/Jail/BaseConfig.py
libioc/Config/Jail/Defaults.py
libioc/Config/Jail/Globals.py
libioc/Config/Jail/JailConfig.py
libioc/Config/Jail/__init__.py
libioc/Config/Jail/File/Fstab.py
libioc/Config/Jail/File/PeriodicConf.py
libioc/Config/Jail/File/RCConf.py
libioc/Config/Jail/File/SysctlConf.py
libioc/Config/Jail/File/__init__.py
libioc/Config/Jail/Properties/Addresses.py
libioc/Config/Jail/Properties/Defaultrouter.py
libioc/Config/Jail/Properties/Depends.py
libioc/Config/Jail/Properties/Interfaces.py
libioc/Config/Jail/Properties/Resolver.py
libioc/Config/Jail/Properties/ResourceLimit.py
libioc/Config/Jail/Properties/__init__.py
libioc/Config/Type/JSON.py
libioc/Config/Type/UCL.py
libioc/Config/Type/ZFS.py
libioc/Config/Type/__init__.py
libioc/Provisioning/__init__.py
libioc/Provisioning/ix.py
libioc/Provisioning/puppet.py
libioc/Storage/Basejail.py
libioc/Storage/NullFSBasejail.py
libioc/Storage/Standalone.py
