Metadata-Version: 1.2
Name: libioc
Version: 0.8.2
Summary: A Python library to manage jails with ioc{age,cell}
Home-page: https://github.com/bsdci/libioc
Author: ioc Contributors
Author-email: authors@libioc.io
License: BSD
Keywords: FreeBSD jail ioc
Platform: UNKNOWN
Requires-Python: >=3.6
